prasbridge/__init__.py
prasbridge/base.py
prasbridge/error.py
prasbridge/mixins.py
prasbridge/session.py
prasbridge/forms/__init__.py
prasbridge/forms/auth.py
prasbridge/forms/fields.py
prasbridge/hashers/__init__.py
prasbridge/hashers/base.py
prasbridge/serializers/__init__.py
prasbridge/serializers/serializers.py
prasbridge/templatetags/__init__.py
prasbridge/templatetags/pras.py
prasbridge/templatetags/helper/__init__.py
prasbridge/templatetags/helper/utils.py
PrasBridge-1.0.5.dist-info/LICENSE.md
PrasBridge-1.0.5.dist-info/METADATA
PrasBridge-1.0.5.dist-info/WHEEL
PrasBridge-1.0.5.dist-info/top_level.txt
PrasBridge-1.0.5.dist-info/RECORD
