Metadata-Version: 2.1
Name: PrasBridge
Version: 1.0.5
Summary: PrasBridge: Simplify project development with a powerful toolkit for integrating SQLAlchemy with Django-style features. Offers serializers, enhanced forms, token generation, hashing, ready-to-use base models and more features. perfect for projects using SQLAlchemy as the main ORM.
Home-page: https://github.com/PRASSamin/PrasBridge
Author: PRAS Samin
Author-email: prassamin@gmail.com
License: MIT
Keywords: Pras,Django,ORM,SQLAlchemy,PrasSerializer,PrasForms,PrasToken,PrasHash,PrasBase,PrasSerializer,PrasForms,PrasToken,PrasHash,PrasBase,PrasBridge
Classifier: Development Status :: 4 - Beta
Classifier: Intended Audience :: Developers
Classifier: Topic :: Software Development :: Build Tools
Classifier: Framework :: Django
Classifier: Programming Language :: Python :: 3
Classifier: Programming Language :: Python :: 3.6
Classifier: Programming Language :: Python :: 3.7
Classifier: Programming Language :: Python :: 3.8
Classifier: License :: OSI Approved :: MIT License
Classifier: Operating System :: OS Independent
Requires-Python: >=3.6
License-File: LICENSE.md
Requires-Dist: Django >=3.2
Requires-Dist: SQLAlchemy >=2.0.35
